{
  "resourceType": "ValueSet",
  "id": "vs-ehealth-usage-context-task-type-tele-wound",
  "url": "http://ehealth.sundhed.dk/vs/ehealth-usage-context-task-type-tele-wound",
  "version": "1.0.0",
  "name": "usageContextTaskTypeTeleWound",
  "title": "Usage Context for Tele Wound Task Type ",
  "status": "active",
  "experimental": false,
  "date": "2026-01-19T00:00:00+00:00",
  "publisher": "ehealth.sundhed.dk",
  "contact": [
    {
      "name": "ehealth.sundhed.dk",
      "telecom": [
        {
          "system": "url",
          "value": "http://ehealth.sundhed.dk/terminology"
        }
      ]
    }
  ],
  "description": "Value set of task types for the Tele Wound domain.",
  "compose": {
    "include": [
      {
        "system": "http://ehealth.sundhed.dk/cs/ehealth-usage-context-task-type"
      }
    ]
  }
}