{
  "resourceType": "ValueSet",
  "id": "ehealth-device-measurement-unit",
  "url": "http://ehealth.sundhed.dk/vs/device-measurement-unit",
  "version": "0.6.0",
  "name": "DeviceMeasurementUnit",
  "title": "Device Measurement Unit",
  "status": "active",
  "experimental": true,
  "date": "2019-09-16T00:00:00+00:00",
  "publisher": "ehealth.sundhed.dk",
  "contact": [
    {
      "name": "ehealth.sundhed.dk",
      "telecom": [
        {
          "system": "url",
          "value": "http://ehealth.sundhed.dk/terminology"
        }
      ]
    }
  ],
  "description": "Device measurement unit",
  "compose": {
    "include": [
      {
        "system": "urn:oid:1.2.208.176.2.1",
        "concept": [
          {
            "code": "NPU03011",
            "display": "Hb(Fe; O2-bind.; aB)—Oxygen(O2); mætn. = ?",
            "designation": [
              {
                "language": "en-US",
                "value": "Oxygen saturation"
              },
              {
                "language": "da",
                "value": "Hb(Fe; O2-bind.; aB)—Oxygen(O2); mætn. = ?"
              }
            ]
          },
          {
            "code": "NPU21692",
            "display": "Hjerte—Systole; frekv. = ? × 1/min",
            "designation": [
              {
                "language": "en-US",
                "value": "Heartbeats per minute"
              },
              {
                "language": "da",
                "value": "Hjerte—Systole; frekv. = ? × 1/min"
              }
            ]
          },
          {
            "code": "NPU03804",
            "display": "Pt—Legeme; masse = ? kg",
            "designation": [
              {
                "language": "en-US",
                "value": "Weight in kilogrammes"
              },
              {
                "language": "da",
                "value": "Pt—Legeme; masse = ? kg"
              }
            ]
          }
        ]
      }
    ]
  }
}