<?xml version="1.0" encoding="utf-8"?>
<StructureDefinition xmlns="http://hl7.org/fhir">
  <id value="dk-tm-patient" />
  <text>
    <status value="additional" />
    <div xmlns="http://www.w3.org/1999/xhtml">This is some additional text</div>
  </text>
  <url value="http://trifork.dk/fhir/StructureDefinition/dk-tm-patient" />
  <name value="Telemedicine patient" />
  <status value="draft" />
  <description value="This profile holds the patient information needed in the danish eHealth context. Patients models the concept of a person in a careplan process. All patients must be linked to an actual person resource instance, where the person acts a template for a patient. A newly created patient is always based from a person which also means that a person links to all its patients.&#xD;&#xA;&#xD;&#xA;#### Creating patients&#xD;&#xA;Patients can only be created using the operations defined for the Patient resource. The operations ensure that patients are created with the proper demographics data, the proper managing organization and under the proper legislation and having a proper link between person and patient." />
  <copyright value="Trifork A/S" />
  <fhirVersion value="3.0.1" />
  <kind value="resource" />
  <abstract value="false" />
  <type value="Patient" />
  <baseDefinition value="http://hl7.org/fhir/StructureDefinition/Patient" />
  <derivation value="constraint" />
  <differential>
    <element id="Patient">
      <path value="Patient" />
    </element>
    <element id="Patient.extension">
      <path value="Patient.extension" />
      <slicing>
        <discriminator>
          <type value="value" />
          <path value="url" />
        </discriminator>
        <rules value="open" />
      </slicing>
    </element>
    <element id="Patient.extension:itcompetencelevel">
      <path value="Patient.extension" />
      <sliceName value="itcompetencelevel" />
      <max value="1" />
      <type>
        <code value="Extension" />
        <profile value="http://ehealth.sundhed.dk/fhir/StructureDefinition/ehealth-itcompetencelevel" />
      </type>
    </element>
    <element id="Patient.extension:itcompetencelevel.valueCodeableConcept:valueCodeableConcept">
      <path value="Patient.extension.valueCodeableConcept" />
      <sliceName value="valueCodeableConcept" />
      <binding>
        <strength value="required" />
        <valueSetUri value="http://ehealth.sundhed.dk/vs/it-selfreliance" />
      </binding>
    </element>
    <element id="Patient.extension:itcompetencelevel.valueCodeableConcept:valueCodeableConcept.coding">
      <path value="Patient.extension.valueCodeableConcept.coding" />
      <binding>
        <strength value="required" />
        <valueSetUri value="http://ehealth.sundhed.dk/vs/it-selfreliance" />
      </binding>
    </element>
    <element id="Patient.extension:interpreterRequired">
      <path value="Patient.extension" />
      <sliceName value="interpreterRequired" />
      <type>
        <code value="Extension" />
        <profile value="http://hl7.org/fhir/StructureDefinition/patient-interpreterRequired" />
      </type>
    </element>
    <element id="Patient.extension:generalHealthCondition">
      <path value="Patient.extension" />
      <sliceName value="generalHealthCondition" />
      <type>
        <code value="Extension" />
        <profile value="http://ehealth.sundhed.dk/fhir/StructureDefinition/ehealth-general-health-condition" />
      </type>
    </element>
    <element id="Patient.extension:functionalCapacity">
      <path value="Patient.extension" />
      <sliceName value="functionalCapacity" />
      <type>
        <code value="Extension" />
        <profile value="http://ehealth.sundhed.dk/fhir/StructureDefinition/ehealth-functional-capacity" />
      </type>
    </element>
    <element id="Patient.identifier">
      <path value="Patient.identifier" />
      <slicing>
        <discriminator>
          <type value="value" />
          <path value="system" />
        </discriminator>
        <rules value="open" />
      </slicing>
      <min value="1" />
      <mustSupport value="true" />
    </element>
    <element id="Patient.identifier:dk-ssn">
      <path value="Patient.identifier" />
      <sliceName value="dk-ssn" />
      <definition value="A technical identifier - identifies some entity uniquely and unambiguously. This identifier holds the social security number defined in a danish context" />
      <min value="1" />
      <max value="1" />
      <type>
        <code value="Identifier" />
        <profile value="http://trifork.dk/fhir/StructureDefinition/dk-tm-ssn-identifier" />
      </type>
    </element>
    <element id="Patient.telecom">
      <path value="Patient.telecom" />
      <slicing>
        <discriminator>
          <type value="value" />
          <path value="value" />
        </discriminator>
        <rules value="open" />
      </slicing>
    </element>
    <element id="Patient.telecom:NemSMS">
      <path value="Patient.telecom" />
      <sliceName value="NemSMS" />
    </element>
    <element id="Patient.telecom:NemSMS.system">
      <path value="Patient.telecom.system" />
      <min value="1" />
      <fixedCode value="other" />
    </element>
    <element id="Patient.telecom:NemSMS.value">
      <path value="Patient.telecom.value" />
      <min value="1" />
      <fixedString value="NemSMS" />
    </element>
    <element id="Patient.telecom:NemSMS.use">
      <path value="Patient.telecom.use" />
      <max value="0" />
    </element>
    <element id="Patient.telecom:NemSMS.rank">
      <path value="Patient.telecom.rank" />
      <max value="0" />
    </element>
    <element id="Patient.telecom:eBoks">
      <path value="Patient.telecom" />
      <sliceName value="eBoks" />
    </element>
    <element id="Patient.telecom:eBoks.system">
      <path value="Patient.telecom.system" />
      <min value="1" />
      <fixedCode value="other" />
    </element>
    <element id="Patient.telecom:eBoks.value">
      <path value="Patient.telecom.value" />
      <min value="1" />
      <fixedString value="eBoks" />
    </element>
    <element id="Patient.telecom:eBoks.use">
      <path value="Patient.telecom.use" />
      <max value="0" />
    </element>
    <element id="Patient.telecom:eBoks.rank">
      <path value="Patient.telecom.rank" />
      <max value="0" />
    </element>
    <element id="Patient.gender">
      <path value="Patient.gender" />
      <min value="1" />
    </element>
    <element id="Patient.address">
      <path value="Patient.address" />
      <slicing>
        <discriminator>
          <type value="value" />
          <path value="use" />
        </discriminator>
        <rules value="open" />
      </slicing>
      <min value="1" />
    </element>
    <element id="Patient.address:officialHomeAddress">
      <path value="Patient.address" />
      <sliceName value="officialHomeAddress" />
      <min value="1" />
      <max value="1" />
      <type>
        <code value="Address" />
        <profile value="http://ehealth.sundhed.dk/fhir/StructureDefinition/ehealth-address" />
      </type>
    </element>
    <element id="Patient.address:officialHomeAddress.extension:municipalityCode">
      <path value="Patient.address.extension" />
      <sliceName value="municipalityCode" />
      <min value="1" />
    </element>
    <element id="Patient.address:officialHomeAddress.extension:regionalSubdivisionCode">
      <path value="Patient.address.extension" />
      <sliceName value="regionalSubdivisionCode" />
      <min value="1" />
    </element>
    <element id="Patient.address:officialHomeAddress.use">
      <path value="Patient.address.use" />
      <fixedCode value="home" />
    </element>
    <element id="Patient.address:temporaryAddress">
      <path value="Patient.address" />
      <sliceName value="temporaryAddress" />
      <type>
        <code value="Address" />
        <profile value="http://ehealth.sundhed.dk/fhir/StructureDefinition/ehealth-address" />
      </type>
    </element>
    <element id="Patient.contact.extension">
      <path value="Patient.contact.extension" />
      <slicing>
        <discriminator>
          <type value="value" />
          <path value="url" />
        </discriminator>
        <rules value="open" />
      </slicing>
    </element>
    <element id="Patient.contact.extension:relatedPerson">
      <path value="Patient.contact.extension" />
      <sliceName value="relatedPerson" />
      <type>
        <code value="Extension" />
        <profile value="http://ehealth.sundhed.dk/fhir/StructureDefinition/ehealth-patient-relatedPerson" />
      </type>
    </element>
    <element id="Patient.contact.extension:contactNote">
      <path value="Patient.contact.extension" />
      <sliceName value="contactNote" />
      <type>
        <code value="Extension" />
        <profile value="http://ehealth.sundhed.dk/fhir/StructureDefinition/ehealth-patient-contactnote" />
      </type>
    </element>
    <element id="Patient.contact.address">
      <path value="Patient.contact.address" />
      <type>
        <code value="Address" />
        <profile value="http://ehealth.sundhed.dk/fhir/StructureDefinition/ehealth-address" />
      </type>
    </element>
    <element id="Patient.animal">
      <extension url="http://hl7.org/fhir/StructureDefinition/structuredefinition-explicit-type-name">
        <valueString value="Animal" />
      </extension>
      <path value="Patient.animal" />
      <max value="0" />
    </element>
    <element id="Patient.communication.language.coding.system">
      <path value="Patient.communication.language.coding.system" />
      <fixedUri value="urn:ietf:bcp:47" />
    </element>
    <element id="Patient.managingOrganization">
      <path value="Patient.managingOrganization" />
      <min value="1" />
      <mustSupport value="true" />
    </element>
  </differential>
</StructureDefinition>