<?xml version="1.0" encoding="utf-8"?>
<StructureDefinition xmlns="http://hl7.org/fhir">
  <id value="ehealth-organization-municipalityCode" />
  <url value="http://ehealth.sundhed.dk/fhir/StructureDefinition/ehealth-organization-municipalityCode" />
  <name value="municipalityCode" />
  <status value="draft" />
  <publisher value="ehealth.sundhed.dk" />
  <description value="The municipalityCode of the organization"/>
  <fhirVersion value="3.0.1" />
  <kind value="complex-type" />
  <abstract value="false" />
  <contextType value="resource" />
  <context value="Organization" />
  <type value="Extension" />
  <baseDefinition value="http://hl7.org/fhir/StructureDefinition/Extension" />
  <derivation value="constraint" />
  <differential>
    <element id="Extension">
      <path value="Extension" />
      <short value="The organization's municipality code in the danish &quot;Det Centrale Personregister&quot;" />
      <definition value="The organization's municipality code in the danish &quot;Det Centrale Personregister&quot;" />
    </element>
    <element id="Extension.url">
      <path value="Extension.url" />
      <fixedUri value="http://ehealth.sundhed.dk/fhir/StructureDefinition/ehealth-organization-municipalityCode" />
    </element>
    <element id="Extension.value[x]:valueString">
      <path value="Extension.valueString" />
      <sliceName value="valueString" />
      <min value="1" />
      <type>
        <code value="string" />
      </type>
    </element>
  </differential>
</StructureDefinition>