{
  "resourceType": "StructureDefinition",
  "id": "ehealth-guidanceresponse",
  "extension": [
    {
      "url": "http://hl7.org/fhir/StructureDefinition/structuredefinition-category",
      "valueString": "Clinical.Request &amp; Response"
    },
    {
      "url": "http://hl7.org/fhir/StructureDefinition/structuredefinition-security-category",
      "valueCode": "patient"
    }
  ],
  "url": "http://ehealth.sundhed.dk/fhir/StructureDefinition/ehealth-guidanceresponse",
  "version": "0.1.0",
  "name": "EhealthGuidanceResponse",
  "title": "eHealth GuidanceResponse",
  "status": "active",
  "description": "eHealth GuidanceResponse",
  "fhirVersion": "4.0.1",
  "mapping": [
    {
      "identity": "workflow",
      "uri": "http://hl7.org/fhir/workflow",
      "name": "Workflow Pattern"
    },
    {
      "identity": "w5",
      "uri": "http://hl7.org/fhir/fivews",
      "name": "FiveWs Pattern Mapping"
    },
    {
      "identity": "rim",
      "uri": "http://hl7.org/v3",
      "name": "RIM Mapping"
    }
  ],
  "kind": "resource",
  "abstract": false,
  "type": "GuidanceResponse",
  "baseDefinition": "http://hl7.org/fhir/StructureDefinition/GuidanceResponse",
  "derivation": "constraint",
  "differential": {
    "element": [
      {
        "id": "GuidanceResponse",
        "path": "GuidanceResponse"
      }
    ]
  }
}
